example_1/shiftleds.v
// Definition of global parameters
// used with C-like syntax and a `
`define N_LEDS 4 	// Number of RGB LEDS to use
`define NB_SEL 2 	//
`define NB_COUNT 32 // Number of bits of counter
`define NB_SW 4 	// Number of switches usage
`define NB_BTN 4 	// Number of buttons

module shiftleds
	// Inicialize global parameters of module with #() before IO assignments
    #(
        parameter  N_LEDS    =  `N_LEDS    ,
        parameter  NB_SEL    =  `NB_SEL    ,
        parameter  NB_COUNT  =  `NB_COUNT  ,
        parameter  NB_BTN    =  `NB_BTN ,
        parameter  NB_SW     =  `NB_SW
    )
	// Assign input/output buses with their respective sizes
    (
        output  [N_LEDS - 1 : 0] o_led_r , // R-color of all LEDS
        output  [N_LEDS - 1 : 0] o_led_b , // B-color of all LEDS
        output  [N_LEDS - 1 : 0] o_led_g , // G-color of all LEDS
        output  [NB_BTN - 1 : 0] o_led   , // Single-terminal LEDS

        input   [NB_SW  - 1 : 0] i_sw    , // Input switches
        input   [NB_BTN - 1 : 0] i_btn   , // input buttons
        input                    clock   , // clock signal
        input                    ck_rst    // reset signal
    );

    // Select shift-speed. Rn will be the amount of clocks to wait until the
	// next generation of a pulse
    localparam R0 = (2**(NB_COUNT-10))-1 ;
    localparam R1 = (2**(NB_COUNT-9)) -1 ;
    localparam R2 = (2**(NB_COUNT-8)) -1 ;
    localparam R3 = (2**(NB_COUNT-7)) -1 ;

    // Speed selector options. This will be linked to switch-values
    localparam SEL0     = `NB_SEL'h0 ; // ex 2'h0 will be 4b'0000
    localparam SEL1     = `NB_SEL'h1 ;
    localparam SEL2     = `NB_SEL'h2 ;
    localparam SEL3     = `NB_SEL'h3 ;


    // Different variables wires/registers to be used
	wire  [NB_COUNT-1:0]  ref_limit      ; // Selected limit (speed)
	reg   [NB_COUNT-1:0]  counter        ; // counter real value
	reg   [N_LEDS-1:0]    shiftreg       ; // shitfreg output (will run LEDS)
	reg   [N_LEDS-1:0]    flash          ; // this will flash leds (i.e. turn all on)
	reg                   sel_SR_FS      ; // select SR=shiftregister or FS=flash mode
	reg                   sel_SR_FS_led  ; // state of LED assosiated to mode-selector
	reg   [3:1]           sel_color      ; // which LED color is turned on
	// sel_color will be which color is chosed to be turned on:
	// 		sel_color[1] is 1'b1 if R
	// 		sel_color[2] is 1'b1 if b
	// 		sel_color[3] is 1'b1 if G
	reg   [3:1]           sel_color_led  ; // LED associated to the button pres

	wire                  init           ; // global enable signal
	wire                  reset          ; // global reset signal

	// CLOCK signal is normal open, so I need to invert it to detect rising
	// edges (or posedges)
    assign reset     =  ~ck_rst;
    assign init      =  i_sw[0]; // First switch will be the enable

	// Select the speed of the SR with i_sw[1:3]
    assign ref_limit = (i_sw[(NB_SW-1)-1 -: NB_SEL]==SEL0) ? R0 :
                       (i_sw[(NB_SW-1)-1 -: NB_SEL]==SEL1) ? R1 :
                       (i_sw[(NB_SW-1)-1 -: NB_SEL]==SEL2) ? R2 : R3;


    //************************************************************
	// This always loop will handle the main logic of the system
	// It will drive the shift=reg, toggle the flash state
    always@(posedge clock or posedge reset) begin
        // RESET signal is chosen to have the greatest priority
        if(reset) begin
            // Inicialize all relevant values
            // Counter = 32'b0 (ex)
            // shiftreg = 4'b0001
            // flash = 4'b0
			//
			// I use <= to have a non-obstructive flow. Everything is
			// connected together and runs "simultaniously"
			//
			// Verilog expansions: {4{1'b0}} == 4'b0000
            counter  <= {NB_COUNT{1'b0}};
            shiftreg <= {{N_LEDS-1{1'b0}},{1'b1}}; // ex 4'b0001
            flash    <= {N_LEDS{1'b0}};
        end
		// Then I check enable signal
        else if(init) begin
            if(counter>=ref_limit)begin
				// Every time the counter reaches the limit it gets reset
				// and then effectibly shift the output and toggle the
				// flash-ed
                counter  <= {NB_COUNT{1'b0}};

                // I will use i_sw[3] to select the shitf direction
                //  0'b0 => 1,2,4,8
                //  1'b0 => 8,4,2,1
                if (i_sw[3] == 1'b0)
					// Abuse Verilog expansions to shift the output state
					// accordingly
                    shiftreg <= {shiftreg[N_LEDS-2 -: N_LEDS-1],shiftreg[N_LEDS-1]};
                else
                    shiftreg <= {shiftreg[0],shiftreg[N_LEDS-1 -: N_LEDS-1]};

				// Toggle the flash state
                flash <= ~flash;
            end
            else begin
                counter  <= counter + {{NB_COUNT-1{1'b0}},{1'b1}};
                shiftreg <= shiftreg;
                flash    <= flash;
            end
        end
        else begin
			// If not init, everything stays the same.
            counter  <= counter;
            shiftreg <= shiftreg;
            flash    <= flash;
        end // if (init)
    end // always@ (posedge clock or posedge reset)


    //************************************************************
	// This handle the mode-selection.
	// It checks the state of the i_btn[0] and and set the according
	// state LED on/off
    always@(posedge clock or posedge reset) begin
        if(reset) begin
			// The reset state is to use the SR to drive the LEDs
			// and to have the state LED off.
            sel_SR_FS <= 1'b0;
            sel_SR_FS_led <= 1'b0;
        end
        else begin
			// i need to generate a buffer register to check for a rising edge
			// on the button press.
			// button_edge = button_state[now] AND ( NOT button_state[now-1])
            sel_SR_FS <= i_btn[0];
            sel_SR_FS_led <= (i_btn[0] && (!sel_SR_FS)) ? !sel_SR_FS_led :
                                                          sel_SR_FS_led  ;

			/*   AWESOME EPIC DRAWING OF AWESOMENESS
			*              _________________     __
			*             |      ______     |___|  )______ sel_SR_FS_led
			* sel_SR_FS___|______|D  Q|_______o_|__)
			*                    |    |           AND
			*              clk___|____|
			*/
        end
    end // always@ (posedge clock or posedge reset)

    //************************************************************
    // This will handle all the color-selection buttons
    always@(posedge clock or posedge reset) begin
        if(reset) begin
			// Reset state is R color
            sel_color_led[3:1] <= 3'b001; // Reseteo para prender solo el r
        end
        else begin
			// Same thing, I need to infer a register to check against
            sel_color[3:1] <= i_btn[3:1];
			// Depending on which button is pressed I HARDCODE the led color
			// state.
			// I don't need to worry about many button presses this way, it
			// always will send the correct output color
            sel_color_led[3:1] <=   (i_btn[1] && (!sel_color[1])) ? 3'b001 :
                                    (i_btn[2] && (!sel_color[2])) ? 3'b010 :
                                    (i_btn[3] && (!sel_color[3])) ? 3'b100 :
                                    sel_color_led[3:1];
        end
    end // always@ (posedge clock or posedge reset)


    //************************************************************
	// OUTPUT assignments.
	// I check if the color is ON. If it is, I check which mode should be
	// acting, if the shifting or the flash

	assign o_led_r = (sel_color_led[1]) ?
						((sel_SR_FS_led) ? flash : shiftreg) :
						4'b0;
	assign o_led_g = (sel_color_led[2]) ?
						((sel_SR_FS_led) ? flash : shiftreg) :
						4'b0;
	assign o_led_b = (sel_color_led[3]) ?
						((sel_SR_FS_led) ? flash : shiftreg) :
						4'b0;

	// this is the "button pressed output LEDS"
	assign o_led = {sel_color_led,sel_SR_FS_led};
endmodule // shiftleds

example_1/tb_shiftleds.v
// Test-Bench of module:
// ShiftLeds
`define N_LEDS   4
`define NB_SEL   2
`define NB_COUNT 14 // I use a lower count number b/c I really don't need 32bit
`define NB_SW    4
`define NB_BTN   4

// Set the timescale to emulate Artix-7 board
`timescale 1ns/100ps

module tb_shiftleds();
	parameter N_LEDS   = `N_LEDS   ;
	parameter NB_SEL   = `NB_SEL   ;
	parameter NB_COUNT = `NB_COUNT ;
	parameter NB_SW    = `NB_SW    ;
	parameter NB_BTN   = `NB_BTN   ;

	// I select all outputs as wires and all inputs as registers.
	// b/c i need them to be stored somewehere, right?
	wire [NB_BTN-1:0]   o_led    ;
	wire [N_LEDS-1:0]   o_led_r  ;
	wire [N_LEDS-1:0]   o_led_b  ;
	wire [N_LEDS-1:0]   o_led_g  ;
	reg  [NB_SW-1 :0]   i_sw     ;
	reg  [NB_BTN-1:0]   i_btn    ;
	reg                 i_reset  ;
	reg                 clock    ;
	wire [NB_COUNT-1:0] tb_count ;

	// get a scope point to register counter value on the waveform
	assign tb_count = tb_shiftleds.u_shiftleds.counter;

	// Run initial to set everything ONCE at first and that's it
	initial begin
		// inicialize inputs
		i_sw[0]    = 1'b0       ; // i_sw[0] = ENABLE
		clock      = 1'b0       ;
		i_reset    = 1'b0       ; // do not reset yet
		i_sw[2:1]  = `NB_SEL'h0 ; // all other switches on 0
		i_sw[3]    = 1'b0       ;
		i_btn[3:0] = 4'b0000    ; // all buttons not pressed

		// wait 100 clocks and set enable and reset
		#100 i_reset = 1'b1;
		#100 i_sw[0] = 1'b1;

		// Begin pressing buttons for 100 clocks (simulating a push and
		// release of a real button).
		// This should probably be better off written on an external file

		// Change mode. SR -> Flash
		#500 i_btn[0] = 1'b1;
		#20  i_btn[0] = 1'b0;

		// Enable RED color (this should already be enabled so nothing must
		// happen)
		#500 i_btn[1] = 1'b1;
		#20  i_btn[1] = 1'b0;

		// Change mode. Flash -> SR
		#500 i_btn[0] = 1'b1;
		#20  i_btn[0] = 1'b0;

		// Enable GREEN color.
		#500 i_btn[2] = 1'b1;
		#20  i_btn[2] = 1'b0;

        // Switch count direction
        #500 i_sw[3]   = 1'b1;
        #20 i_sw[3]   = 1'b1;

		// Change mode. SR -> Flash
		#500 i_btn[0] = 1'b1;
		#20  i_btn[0] = 1'b0;

		// Enable BLUE color
		#500 i_btn[3] = 1'b1;
		#20  i_btn[3] = 1'b0;

		// Change mode. Flash -> SR
		#500 i_btn[0] = 1'b1;
		#20  i_btn[0] = 1'b0;

		// Wait and finish
		#100 $finish;
	end

	// Select the clock frecuency 5clocks HIGH 5clocks LOW.
	// each clock is 1ns, so 10ns clock period
	always #5 clock = ~clock;

	// Instance shiftleds module
	shiftleds
		// Set the global vraiables
	  #(
		  .N_LEDS   (N_LEDS  ),
		  .NB_SEL   (NB_SEL  ),
		  .NB_COUNT (NB_COUNT),
		  .NB_SW    (NB_SW   )
	  )
	  // select instance name and connect all end-points to test-bench
	  // registers/wires
	  u_shiftleds
	  (
		  .o_led     (o_led  ),
		  .o_led_r   (o_led_r),
		  .o_led_b   (o_led_b),
		  .o_led_g   (o_led_g),
		  .i_sw      (i_sw   ),
		  .i_btn     (i_btn  ),
		  .ck_rst    (i_reset),
		  .clock     (clock  )
	  );

endmodule // tb_shiftleds

example_1/logs/test_waveform.vcd
$date
   Fri Mar  5 19:50:07 2021
$end
$version
  2019.2
$end
$timescale
  1ps
$end
$scope module tb_shiftleds $end
$var wire 4 $ o_led [3:0] $end
$var wire 4 ! o_led_r [3:0] $end
$var wire 4 " o_led_b [3:0] $end
$var wire 4 # o_led_g [3:0] $end
$var reg 4 @ i_sw [3:0] $end
$var reg 4 A i_btn [3:0] $end
$var reg 1 B i_reset $end
$var reg 1 C clock $end
$var wire 14 D tb_count [13:0] $end
$var parameter 32 E N_LEDS [31:0] $end
$var parameter 32 F NB_SEL [31:0] $end
$var parameter 32 G NB_COUNT [31:0] $end
$var parameter 32 H NB_SW [31:0] $end
$var parameter 32 I NB_BTN [31:0] $end
$scope module u_shiftleds $end
$var wire 4 ! o_led_r [3:0] $end
$var wire 4 " o_led_b [3:0] $end
$var wire 4 # o_led_g [3:0] $end
$var wire 4 $ o_led [3:0] $end
$var wire 4 % i_sw [3:0] $end
$var wire 4 & i_btn [3:0] $end
$var wire 1 ' clock $end
$var wire 1 ( ck_rst $end
$var wire 14 ) ref_limit [13:0] $end
$var reg 14 * counter [13:0] $end
$var reg 4 + shiftreg [3:0] $end
$var reg 4 , flash [3:0] $end
$var reg 1 - sel_SR_FS $end
$var reg 1 . sel_SR_FS_led $end
$var reg 3 / sel_color [3:1] $end
$var reg 3 0 sel_color_led [3:1] $end
$var wire 1 1 init $end
$var wire 1 2 reset $end
$var parameter 32 3 N_LEDS [31:0] $end
$var parameter 32 4 NB_SEL [31:0] $end
$var parameter 32 5 NB_COUNT [31:0] $end
$var parameter 32 6 NB_BTN [31:0] $end
$var parameter 32 7 NB_SW [31:0] $end
$var parameter 32 8 R0 [31:0] $end
$var parameter 32 9 R1 [31:0] $end
$var parameter 32 : R2 [31:0] $end
$var parameter 32 ; R3 [31:0] $end
$var parameter 2 < SEL0 [1:0] $end
$var parameter 2 = SEL1 [1:0] $end
$var parameter 2 > SEL2 [1:0] $end
$var parameter 2 ? SEL3 [1:0] $end
$upscope $end
$upscope $end
$enddefinitions $end
#0
$dumpvars
b1 !
b0 "
b0 #
b10 $
b0 %
b0 &
0'
0(
b1111 )
b0 *
b1 +
b0 ,
0-
0.
bx /
b1 0
01
12
b100 3
b10 4
b1110 5
b100 6
b100 7
b1111 8
b11111 9
b111111 :
b1111111 ;
b0 <
b1 =
b10 >
b11 ?
b0 @
b0 A
0B
0C
b0 D
b100 E
b10 F
b1110 G
b100 H
b100 I
$end
#5000
1'
1C
#10000
0'
0C
#15000
1'
1C
#20000
0'
0C
#25000
1'
1C
#30000
0'
0C
#35000
1'
1C
#40000
0'
0C
#45000
1'
1C
#50000
0'
0C
#55000
1'
1C
#60000
0'
0C
#65000
1'
1C
#70000
0'
0C
#75000
1'
1C
#80000
0'
0C
#85000
1'
1C
#90000
0'
0C
#95000
1'
1C
#100000
0'
1(
02
1B
0C
#105000
1'
b0 /
1C
#110000
0'
0C
#115000
1'
1C
#120000
0'
0C
#125000
1'
1C
#130000
0'
0C
#135000
1'
1C
#140000
0'
0C
#145000
1'
1C
#150000
0'
0C
#155000
1'
1C
#160000
0'
0C
#165000
1'
1C
#170000
0'
0C
#175000
1'
1C
#180000
0'
0C
#185000
1'
1C
#190000
0'
0C
#195000
1'
1C
#200000
b1 %
0'
11
b1 @
0C
#205000
1'
b1 *
1C
b1 D
#210000
0'
0C
#215000
1'
b10 *
1C
b10 D
#220000
0'
0C
#225000
1'
b11 *
1C
b11 D
#230000
0'
0C
#235000
1'
b100 *
1C
b100 D
#240000
0'
0C
#245000
1'
b101 *
1C
b101 D
#250000
0'
0C
#255000
1'
b110 *
1C
b110 D
#260000
0'
0C
#265000
1'
b111 *
1C
b111 D
#270000
0'
0C
#275000
1'
b1000 *
1C
b1000 D
#280000
0'
0C
#285000
1'
b1001 *
1C
b1001 D
#290000
0'
0C
#295000
1'
b1010 *
1C
b1010 D
#300000
0'
0C
#305000
1'
b1011 *
1C
b1011 D
#310000
0'
0C
#315000
1'
b1100 *
1C
b1100 D
#320000
0'
0C
#325000
1'
b1101 *
1C
b1101 D
#330000
0'
0C
#335000
1'
b1110 *
1C
b1110 D
#340000
0'
0C
#345000
1'
b1111 *
1C
b1111 D
#350000
0'
0C
#355000
b10 !
1'
b0 *
b10 +
b1111 ,
1C
b0 D
#360000
0'
0C
#365000
1'
b1 *
1C
b1 D
#370000
0'
0C
#375000
1'
b10 *
1C
b10 D
#380000
0'
0C
#385000
1'
b11 *
1C
b11 D
#390000
0'
0C
#395000
1'
b100 *
1C
b100 D
#400000
0'
0C
#405000
1'
b101 *
1C
b101 D
#410000
0'
0C
#415000
1'
b110 *
1C
b110 D
#420000
0'
0C
#425000
1'
b111 *
1C
b111 D
#430000
0'
0C
#435000
1'
b1000 *
1C
b1000 D
#440000
0'
0C
#445000
1'
b1001 *
1C
b1001 D
#450000
0'
0C
#455000
1'
b1010 *
1C
b1010 D
#460000
0'
0C
#465000
1'
b1011 *
1C
b1011 D
#470000
0'
0C
#475000
1'
b1100 *
1C
b1100 D
#480000
0'
0C
#485000
1'
b1101 *
1C
b1101 D
#490000
0'
0C
#495000
1'
b1110 *
1C
b1110 D
#500000
0'
0C
#505000
1'
b1111 *
1C
b1111 D
#510000
0'
0C
#515000
b100 !
1'
b0 *
b100 +
b0 ,
1C
b0 D
#520000
0'
0C
#525000
1'
b1 *
1C
b1 D
#530000
0'
0C
#535000
1'
b10 *
1C
b10 D
#540000
0'
0C
#545000
1'
b11 *
1C
b11 D
#550000
0'
0C
#555000
1'
b100 *
1C
b100 D
#560000
0'
0C
#565000
1'
b101 *
1C
b101 D
#570000
0'
0C
#575000
1'
b110 *
1C
b110 D
#580000
0'
0C
#585000
1'
b111 *
1C
b111 D
#590000
0'
0C
#595000
1'
b1000 *
1C
b1000 D
#600000
0'
0C
#605000
1'
b1001 *
1C
b1001 D
#610000
0'
0C
#615000
1'
b1010 *
1C
b1010 D
#620000
0'
0C
#625000
1'
b1011 *
1C
b1011 D
#630000
0'
0C
#635000
1'
b1100 *
1C
b1100 D
#640000
0'
0C
#645000
1'
b1101 *
1C
b1101 D
#650000
0'
0C
#655000
1'
b1110 *
1C
b1110 D
#660000
0'
0C
#665000
1'
b1111 *
1C
b1111 D
#670000
0'
0C
#675000
b1000 !
1'
b0 *
b1000 +
b1111 ,
1C
b0 D
#680000
0'
0C
#685000
1'
b1 *
1C
b1 D
#690000
0'
0C
#695000
1'
b10 *
1C
b10 D
#700000
b1 &
0'
b1 A
0C
#705000
b1111 !
b11 $
1'
b11 *
1-
1.
1C
b11 D
#710000
0'
0C
#715000
1'
b100 *
1C
b100 D
#720000
b0 &
0'
b0 A
0C
#725000
1'
b101 *
0-
1C
b101 D
#730000
0'
0C
#735000
1'
b110 *
1C
b110 D
#740000
0'
0C
#745000
1'
b111 *
1C
b111 D
#750000
0'
0C
#755000
1'
b1000 *
1C
b1000 D
#760000
0'
0C
#765000
1'
b1001 *
1C
b1001 D
#770000
0'
0C
#775000
1'
b1010 *
1C
b1010 D
#780000
0'
0C
#785000
1'
b1011 *
1C
b1011 D
#790000
0'
0C
#795000
1'
b1100 *
1C
b1100 D
#800000
0'
0C
#805000
1'
b1101 *
1C
b1101 D
#810000
0'
0C
#815000
1'
b1110 *
1C
b1110 D
#820000
0'
0C
#825000
1'
b1111 *
1C
b1111 D
#830000
0'
0C
#835000
b0 !
1'
b0 *
b1 +
b0 ,
1C
b0 D
#840000
0'
0C
#845000
1'
b1 *
1C
b1 D
#850000
0'
0C
#855000
1'
b10 *
1C
b10 D
#860000
0'
0C
#865000
1'
b11 *
1C
b11 D
#870000
0'
0C
#875000
1'
b100 *
1C
b100 D
#880000
0'
0C
#885000
1'
b101 *
1C
b101 D
#890000
0'
0C
#895000
1'
b110 *
1C
b110 D
#900000
0'
0C
#905000
1'
b111 *
1C
b111 D
#910000
0'
0C
#915000
1'
b1000 *
1C
b1000 D
#920000
0'
0C
#925000
1'
b1001 *
1C
b1001 D
#930000
0'
0C
#935000
1'
b1010 *
1C
b1010 D
#940000
0'
0C
#945000
1'
b1011 *
1C
b1011 D
#950000
0'
0C
#955000
1'
b1100 *
1C
b1100 D
#960000
0'
0C
#965000
1'
b1101 *
1C
b1101 D
#970000
0'
0C
#975000
1'
b1110 *
1C
b1110 D
#980000
0'
0C
#985000
1'
b1111 *
1C
b1111 D
#990000
0'
0C
#995000
b1111 !
1'
b0 *
b10 +
b1111 ,
1C
b0 D
#1000000
0'
0C
#1005000
1'
b1 *
1C
b1 D
#1010000
0'
0C
#1015000
1'
b10 *
1C
b10 D
#1020000
0'
0C
#1025000
1'
b11 *
1C
b11 D
#1030000
0'
0C
#1035000
1'
b100 *
1C
b100 D
#1040000
0'
0C
#1045000
1'
b101 *
1C
b101 D
#1050000
0'
0C
#1055000
1'
b110 *
1C
b110 D
#1060000
0'
0C
#1065000
1'
b111 *
1C
b111 D
#1070000
0'
0C
#1075000
1'
b1000 *
1C
b1000 D
#1080000
0'
0C
#1085000
1'
b1001 *
1C
b1001 D
#1090000
0'
0C
#1095000
1'
b1010 *
1C
b1010 D
#1100000
0'
0C
#1105000
1'
b1011 *
1C
b1011 D
#1110000
0'
0C
#1115000
1'
b1100 *
1C
b1100 D
#1120000
0'
0C
#1125000
1'
b1101 *
1C
b1101 D
#1130000
0'
0C
#1135000
1'
b1110 *
1C
b1110 D
#1140000
0'
0C
#1145000
1'
b1111 *
1C
b1111 D
#1150000
0'
0C
#1155000
b0 !
1'
b0 *
b100 +
b0 ,
1C
b0 D
#1160000
0'
0C
#1165000
1'
b1 *
1C
b1 D
#1170000
0'
0C
#1175000
1'
b10 *
1C
b10 D
#1180000
0'
0C
#1185000
1'
b11 *
1C
b11 D
#1190000
0'
0C
#1195000
1'
b100 *
1C
b100 D
#1200000
0'
0C
#1205000
1'
b101 *
1C
b101 D
#1210000
0'
0C
#1215000
1'
b110 *
1C
b110 D
#1220000
b10 &
0'
b10 A
0C
#1225000
1'
b111 *
b1 /
1C
b111 D
#1230000
0'
0C
#1235000
1'
b1000 *
1C
b1000 D
#1240000
b0 &
0'
b0 A
0C
#1245000
1'
b1001 *
b0 /
1C
b1001 D
#1250000
0'
0C
#1255000
1'
b1010 *
1C
b1010 D
#1260000
0'
0C
#1265000
1'
b1011 *
1C
b1011 D
#1270000
0'
0C
#1275000
1'
b1100 *
1C
b1100 D
#1280000
0'
0C
#1285000
1'
b1101 *
1C
b1101 D
#1290000
0'
0C
#1295000
1'
b1110 *
1C
b1110 D
#1300000
0'
0C
#1305000
1'
b1111 *
1C
b1111 D
#1310000
0'
0C
#1315000
b1111 !
1'
b0 *
b1000 +
b1111 ,
1C
b0 D
#1320000
0'
0C
#1325000
1'
b1 *
1C
b1 D
#1330000
0'
0C
#1335000
1'
b10 *
1C
b10 D
#1340000
0'
0C
#1345000
1'
b11 *
1C
b11 D
#1350000
0'
0C
#1355000
1'
b100 *
1C
b100 D
#1360000
0'
0C
#1365000
1'
b101 *
1C
b101 D
#1370000
0'
0C
#1375000
1'
b110 *
1C
b110 D
#1380000
0'
0C
#1385000
1'
b111 *
1C
b111 D
#1390000
0'
0C
#1395000
1'
b1000 *
1C
b1000 D
#1400000
0'
0C
#1405000
1'
b1001 *
1C
b1001 D
#1410000
0'
0C
#1415000
1'
b1010 *
1C
b1010 D
#1420000
0'
0C
#1425000
1'
b1011 *
1C
b1011 D
#1430000
0'
0C
#1435000
1'
b1100 *
1C
b1100 D
#1440000
0'
0C
#1445000
1'
b1101 *
1C
b1101 D
#1450000
0'
0C
#1455000
1'
b1110 *
1C
b1110 D
#1460000
0'
0C
#1465000
1'
b1111 *
1C
b1111 D
#1470000
0'
0C
#1475000
b0 !
1'
b0 *
b1 +
b0 ,
1C
b0 D
#1480000
0'
0C
#1485000
1'
b1 *
1C
b1 D
#1490000
0'
0C
#1495000
1'
b10 *
1C
b10 D
#1500000
0'
0C
#1505000
1'
b11 *
1C
b11 D
#1510000
0'
0C
#1515000
1'
b100 *
1C
b100 D
#1520000
0'
0C
#1525000
1'
b101 *
1C
b101 D
#1530000
0'
0C
#1535000
1'
b110 *
1C
b110 D
#1540000
0'
0C
#1545000
1'
b111 *
1C
b111 D
#1550000
0'
0C
#1555000
1'
b1000 *
1C
b1000 D
#1560000
0'
0C
#1565000
1'
b1001 *
1C
b1001 D
#1570000
0'
0C
#1575000
1'
b1010 *
1C
b1010 D
#1580000
0'
0C
#1585000
1'
b1011 *
1C
b1011 D
#1590000
0'
0C
#1595000
1'
b1100 *
1C
b1100 D
#1600000
0'
0C
#1605000
1'
b1101 *
1C
b1101 D
#1610000
0'
0C
#1615000
1'
b1110 *
1C
b1110 D
#1620000
0'
0C
#1625000
1'
b1111 *
1C
b1111 D
#1630000
0'
0C
#1635000
b1111 !
1'
b0 *
b10 +
b1111 ,
1C
b0 D
#1640000
0'
0C
#1645000
1'
b1 *
1C
b1 D
#1650000
0'
0C
#1655000
1'
b10 *
1C
b10 D
#1660000
0'
0C
#1665000
1'
b11 *
1C
b11 D
#1670000
0'
0C
#1675000
1'
b100 *
1C
b100 D
#1680000
0'
0C
#1685000
1'
b101 *
1C
b101 D
#1690000
0'
0C
#1695000
1'
b110 *
1C
b110 D
#1700000
0'
0C
#1705000
1'
b111 *
1C
b111 D
#1710000
0'
0C
#1715000
1'
b1000 *
1C
b1000 D
#1720000
0'
0C
#1725000
1'
b1001 *
1C
b1001 D
#1730000
0'
0C
#1735000
1'
b1010 *
1C
b1010 D
#1740000
b1 &
0'
b1 A
0C
#1745000
b10 !
b10 $
1'
b1011 *
1-
0.
1C
b1011 D
#1750000
0'
0C
#1755000
1'
b1100 *
1C
b1100 D
#1760000
b0 &
0'
b0 A
0C
#1765000
1'
b1101 *
0-
1C
b1101 D
#1770000
0'
0C
#1775000
1'
b1110 *
1C
b1110 D
#1780000
0'
0C
#1785000
1'
b1111 *
1C
b1111 D
#1790000
0'
0C
#1795000
b100 !
1'
b0 *
b100 +
b0 ,
1C
b0 D
#1800000
0'
0C
#1805000
1'
b1 *
1C
b1 D
#1810000
0'
0C
#1815000
1'
b10 *
1C
b10 D
#1820000
0'
0C
#1825000
1'
b11 *
1C
b11 D
#1830000
0'
0C
#1835000
1'
b100 *
1C
b100 D
#1840000
0'
0C
#1845000
1'
b101 *
1C
b101 D
#1850000
0'
0C
#1855000
1'
b110 *
1C
b110 D
#1860000
0'
0C
#1865000
1'
b111 *
1C
b111 D
#1870000
0'
0C
#1875000
1'
b1000 *
1C
b1000 D
#1880000
0'
0C
#1885000
1'
b1001 *
1C
b1001 D
#1890000
0'
0C
#1895000
1'
b1010 *
1C
b1010 D
#1900000
0'
0C
#1905000
1'
b1011 *
1C
b1011 D
#1910000
0'
0C
#1915000
1'
b1100 *
1C
b1100 D
#1920000
0'
0C
#1925000
1'
b1101 *
1C
b1101 D
#1930000
0'
0C
#1935000
1'
b1110 *
1C
b1110 D
#1940000
0'
0C
#1945000
1'
b1111 *
1C
b1111 D
#1950000
0'
0C
#1955000
b1000 !
1'
b0 *
b1000 +
b1111 ,
1C
b0 D
#1960000
0'
0C
#1965000
1'
b1 *
1C
b1 D
#1970000
0'
0C
#1975000
1'
b10 *
1C
b10 D
#1980000
0'
0C
#1985000
1'
b11 *
1C
b11 D
#1990000
0'
0C
#1995000
1'
b100 *
1C
b100 D
#2000000
0'
0C
#2005000
1'
b101 *
1C
b101 D
#2010000
0'
0C
#2015000
1'
b110 *
1C
b110 D
#2020000
0'
0C
#2025000
1'
b111 *
1C
b111 D
#2030000
0'
0C
#2035000
1'
b1000 *
1C
b1000 D
#2040000
0'
0C
#2045000
1'
b1001 *
1C
b1001 D
#2050000
0'
0C
#2055000
1'
b1010 *
1C
b1010 D
#2060000
0'
0C
#2065000
1'
b1011 *
1C
b1011 D
#2070000
0'
0C
#2075000
1'
b1100 *
1C
b1100 D
#2080000
0'
0C
#2085000
1'
b1101 *
1C
b1101 D
#2090000
0'
0C
#2095000
1'
b1110 *
1C
b1110 D
#2100000
0'
0C
#2105000
1'
b1111 *
1C
b1111 D
#2110000
0'
0C
#2115000
b1 !
1'
b0 *
b1 +
b0 ,
1C
b0 D
#2120000
0'
0C
#2125000
1'
b1 *
1C
b1 D
#2130000
0'
0C
#2135000
1'
b10 *
1C
b10 D
#2140000
0'
0C
#2145000
1'
b11 *
1C
b11 D
#2150000
0'
0C
#2155000
1'
b100 *
1C
b100 D
#2160000
0'
0C
#2165000
1'
b101 *
1C
b101 D
#2170000
0'
0C
#2175000
1'
b110 *
1C
b110 D
#2180000
0'
0C
#2185000
1'
b111 *
1C
b111 D
#2190000
0'
0C
#2195000
1'
b1000 *
1C
b1000 D
#2200000
0'
0C
#2205000
1'
b1001 *
1C
b1001 D
#2210000
0'
0C
#2215000
1'
b1010 *
1C
b1010 D
#2220000
0'
0C
#2225000
1'
b1011 *
1C
b1011 D
#2230000
0'
0C
#2235000
1'
b1100 *
1C
b1100 D
#2240000
0'
0C
#2245000
1'
b1101 *
1C
b1101 D
#2250000
0'
0C
#2255000
1'
b1110 *
1C
b1110 D
#2260000
b100 &
0'
b100 A
0C
#2265000
b0 !
b1 #
b100 $
1'
b1111 *
b10 /
b10 0
1C
b1111 D
#2270000
0'
0C
#2275000
b10 #
1'
b0 *
b10 +
b1111 ,
1C
b0 D
#2280000
b0 &
0'
b0 A
0C
#2285000
1'
b1 *
b0 /
1C
b1 D
#2290000
0'
0C
#2295000
1'
b10 *
1C
b10 D
#2300000
0'
0C
#2305000
1'
b11 *
1C
b11 D
#2310000
0'
0C
#2315000
1'
b100 *
1C
b100 D
#2320000
0'
0C
#2325000
1'
b101 *
1C
b101 D
#2330000
0'
0C
#2335000
1'
b110 *
1C
b110 D
#2340000
0'
0C
#2345000
1'
b111 *
1C
b111 D
#2350000
0'
0C
#2355000
1'
b1000 *
1C
b1000 D
#2360000
0'
0C
#2365000
1'
b1001 *
1C
b1001 D
#2370000
0'
0C
#2375000
1'
b1010 *
1C
b1010 D
#2380000
0'
0C
#2385000
1'
b1011 *
1C
b1011 D
#2390000
0'
0C
#2395000
1'
b1100 *
1C
b1100 D
#2400000
0'
0C
#2405000
1'
b1101 *
1C
b1101 D
#2410000
0'
0C
#2415000
1'
b1110 *
1C
b1110 D
#2420000
0'
0C
#2425000
1'
b1111 *
1C
b1111 D
#2430000
0'
0C
#2435000
b100 #
1'
b0 *
b100 +
b0 ,
1C
b0 D
#2440000
0'
0C
#2445000
1'
b1 *
1C
b1 D
#2450000
0'
0C
#2455000
1'
b10 *
1C
b10 D
#2460000
0'
0C
#2465000
1'
b11 *
1C
b11 D
#2470000
0'
0C
#2475000
1'
b100 *
1C
b100 D
#2480000
0'
0C
#2485000
1'
b101 *
1C
b101 D
#2490000
0'
0C
#2495000
1'
b110 *
1C
b110 D
#2500000
0'
0C
#2505000
1'
b111 *
1C
b111 D
#2510000
0'
0C
#2515000
1'
b1000 *
1C
b1000 D
#2520000
0'
0C
#2525000
1'
b1001 *
1C
b1001 D
#2530000
0'
0C
#2535000
1'
b1010 *
1C
b1010 D
#2540000
0'
0C
#2545000
1'
b1011 *
1C
b1011 D
#2550000
0'
0C
#2555000
1'
b1100 *
1C
b1100 D
#2560000
0'
0C
#2565000
1'
b1101 *
1C
b1101 D
#2570000
0'
0C
#2575000
1'
b1110 *
1C
b1110 D
#2580000
0'
0C
#2585000
1'
b1111 *
1C
b1111 D
#2590000
0'
0C
#2595000
b1000 #
1'
b0 *
b1000 +
b1111 ,
1C
b0 D
#2600000
0'
0C
#2605000
1'
b1 *
1C
b1 D
#2610000
0'
0C
#2615000
1'
b10 *
1C
b10 D
#2620000
0'
0C
#2625000
1'
b11 *
1C
b11 D
#2630000
0'
0C
#2635000
1'
b100 *
1C
b100 D
#2640000
0'
0C
